{
  "foods": [
    {
      "id": 1,
      "available": true,
      "image": "https://storage.googleapis.com/golden-wind/bootcamp-gostack/desafio-food/food1.png",
      "name": "Ao molho",
      "price": "20.00",
      "description": "Macarrão ao molho branco, fughi e cheiro verde das montanhas."
    },
    {
      "id": 2,
      "available": true,
      "image": "https://storage.googleapis.com/golden-wind/bootcamp-gostack/desafio-food/food2.png",
      "name": "Veggie",
      "price": "21.92",
      "description": "Macarrão com pimentão, ervilha e ervas finas colhidas no himalaia."
    },
    {
      "image": "https://storage.googleapis.com/golden-wind/bootcamp-gostack/desafio-food/food3.png",
      "name": "A la Camarón",
      "price": "12.54",
      "description": "Macarrão com vegetais de primeira linha e camarão dos 7 mares.",
      "available": true,
      "id": 3
    }
  ]
}